{"id": "house_randy_neugebauer", "name": "Randy Neugebauer", "party": "R", "chamber": "House", "active": false, "photo": "https://unitedstates.github.io/images/congress/225x275/N000182.jpg", "elo": 1482, "matches": 21, "wins": 8, "losses": 12, "ties": 1, "winrate": 38.1, "sharp": 0, "n_buys": 15, "buy_winrate": 40.0, "n_sells": 6, "sell_winrate": 33.3, "committees": [], "trades": [{"date": "2016-11-14", "side": "buy", "ticker": "SLV", "company": "iShares Silver Trust", "sector": "", "excess": -8.0, "ex30": -4.6, "sharp": false}, {"date": "2016-08-26", "side": "buy", "ticker": "SLV", "company": "iShares Silver Trust", "sector": "", "excess": -2.3, "ex30": 5.0, "sharp": false}, {"date": "2016-07-12", "side": "buy", "ticker": "GS", "company": "AlaskaP04/12/201604/13/2016$100,001 - $250,000 FILING STATUS: Amended KINGDOM ENTERPRISES, LTD, LUBBOCK, TEXAS - INVESTMENT PARTNERSHIP >", "sector": "Finance", "excess": 10.9, "ex30": 2.9, "sharp": false}, {"date": "2016-06-29", "side": "buy", "ticker": "FFIN", "company": "First Financial Bankshares, Inc.", "sector": "Finance", "excess": 5.2, "ex30": 2.6, "sharp": false}, {"date": "2016-06-27", "side": "buy", "ticker": "FFIN", "company": "First Financial Bankshares, Inc.", "sector": "Finance", "excess": 9.0, "ex30": 8.7, "sharp": false}, {"date": "2016-06-23", "side": "sell", "ticker": "FFIN", "company": "First Financial Bankshares, Inc.", "sector": "Finance", "excess": -0.3, "ex30": -0.5, "sharp": false}, {"date": "2016-06-15", "side": "sell", "ticker": "GLD", "company": "DR Gold Trust", "sector": "", "excess": 7.8, "ex30": 1.8, "sharp": false}, {"date": "2016-05-25", "side": "sell", "ticker": "IP", "company": "International Paper Company", "sector": "Basic Materials", "excess": -0.5, "ex30": -0.7, "sharp": false}, {"date": "2016-03-28", "side": "sell", "ticker": "COP", "company": "ConocoPhillips", "sector": "Energy", "excess": -11.5, "ex30": -18.4, "sharp": false}, {"date": "2016-01-22", "side": "buy", "ticker": "FFIN", "company": "First Financial Bankshares, Inc.", "sector": "Finance", "excess": 9.1, "ex30": 2.2, "sharp": false}, {"date": "2015-11-10", "side": "buy", "ticker": "GS", "company": "Chicago Illinois Brd of Edu Go 5% 12/01/16 S11/4/201511/5/2015$100,001 - $250,000 FILING STaTUS: New KINGDoM ENTERPRISES, LTD, LUBBoCK, TEXaS - INVESTMENT PaRTNERSHIP>", "sector": "Finance", "excess": -4.4, "ex30": -6.5, "sharp": false}, {"date": "2015-07-20", "side": "buy", "ticker": "GLD", "company": "DR Gold Trust", "sector": "", "excess": 7.9, "ex30": 5.0, "sharp": false}, {"date": "2015-05-13", "side": "buy", "ticker": "FFIN", "company": "BRoKERaGE aCCoUNT - TD aMERITRaDE First Financial Bankshares, Inc.", "sector": "Finance", "excess": 7.0, "ex30": 9.9, "sharp": false}, {"date": "2015-04-21", "side": "buy", "ticker": "IP", "company": "International Paper Company", "sector": "Basic Materials", "excess": -6.5, "ex30": -0.5, "sharp": false}, {"date": "2015-01-29", "side": "buy", "ticker": "COP", "company": "ConocoPhillips", "sector": "Energy", "excess": -11.0, "ex30": -2.2, "sharp": false}, {"date": "2015-01-29", "side": "buy", "ticker": "COP", "company": "ConocoPhillips", "sector": "Energy", "excess": -11.0, "ex30": -2.2, "sharp": false}, {"date": "2015-01-29", "side": "buy", "ticker": "COP", "company": "BRoKERaGE aCCoUNT - TD aMERITRaDE 2000006353ConocoPhillips", "sector": "Energy", "excess": -11.0, "ex30": -2.2, "sharp": false}, {"date": "2014-12-22", "side": "sell", "ticker": "GS", "company": "BRoKERaGE aCCoUNT - GoLDMaN SaCHS HoLDINGS 25% 08/01/2020 USD SER B SR LIEN M-W+50.00BP", "sector": "Finance", "excess": 4.3, "ex30": 6.7, "sharp": false}, {"date": "2014-09-30", "side": "buy", "ticker": "SLV", "company": "iShares Silver Trust", "sector": "", "excess": -7.9, "ex30": -4.4, "sharp": false}, {"date": "2014-09-30", "side": "buy", "ticker": "SLV", "company": "CHS BROKERAGE RETIREMENT ACCOUNT iShares Silver Trust", "sector": "", "excess": -7.9, "ex30": -4.4, "sharp": false}, {"date": "2014-05-23", "side": "sell", "ticker": "GS", "company": "KINGDoM ENTERPRISES, LTD, LUBBoCK, TEXaS - INVESTMENT PaRTNERSHIP>", "sector": "Finance", "excess": -8.1, "ex30": -3.0, "sharp": false}]}